naverscrap
