Metadata-Version: 2.1
Name: naverscrap
Version: 1.0.6
Summary: A Naver News Scraping tool
Home-page: https://github.com/brendonlch/naverscrap
Author: Brendon Lim
Author-email: brendonlim96@hotmail.com
License: MIT
Download-URL: https://github.com/brendonlch/naverscrap/archive/refs/tags/1.0.6.tar.gz
Keywords: naver,korea,news,article,newspaper,web scrapping,web crawl,crawl,search
Platform: UNKNOWN
Classifier: Development Status :: 4 - Beta
Classifier: Intended Audience :: Developers
Classifier: Topic :: Software Development :: Build Tools
Classifier: License :: OSI Approved :: MIT License
Classifier: Programming Language :: Python :: 3
Classifier: Programming Language :: Python :: 3.4
Classifier: Programming Language :: Python :: 3.5
Classifier: Programming Language :: Python :: 3.6
Classifier: Programming Language :: Python :: 3.7
Classifier: Programming Language :: Python :: 3.8
Classifier: Programming Language :: Python :: 3.9
